plasma_system_ai/__init__.py
plasma_system_ai/main-fregio.py
plasma_system_ai/plasma_start.py
plasma_system_ai/writereadout-tens.py
plasma_system_ai/writereadout_tens.py
plasma_ai-1.0.1.dist-info/METADATA
plasma_ai-1.0.1.dist-info/WHEEL
plasma_ai-1.0.1.dist-info/entry_points.txt
plasma_ai-1.0.1.dist-info/top_level.txt
plasma_ai-1.0.1.dist-info/RECORD
