Metadata-Version: 2.4
Name: Plasma-AI
Version: 1.0.1
Summary: DE-AI: An intelligent Linux desktop AI system that manages and optimizes your environment.
Home-page: https://github.com/Zamanhuseyinli/Linux-AI
Author: Zaman Huseyinli
Author-email: admin@azccriminal.space
License: GPLv2
Classifier: Programming Language :: Python :: 3
Classifier: License :: OSI Approved :: GNU General Public License v2 (GPLv2)
Classifier: Operating System :: POSIX :: Linux
Classifier: Intended Audience :: Developers
Classifier: Topic :: System :: Monitoring
Classifier: Topic :: System :: Operating System Kernels :: Linux
Classifier: Topic :: Software Development :: Libraries :: Application Frameworks
Requires-Python: >=3.7
Requires-Dist: psutil
Requires-Dist: tensorflow
Dynamic: author
Dynamic: author-email
Dynamic: classifier
Dynamic: description
Dynamic: description-content-type
Dynamic: home-page
Dynamic: license
Dynamic: requires-dist
Dynamic: requires-python
Dynamic: summary
